toomanysessions/__init__.py
toomanysessions/core.py
toomanysessions/msft_oauth.py
toomanysessions/passkey.py
toomanysessions/pkg_json_router/__init__.py
toomanysessions/pkg_json_router/mod_json_router.py
toomanysessions/sessions.py
toomanysessions/templates/app.css
toomanysessions/templates/app.js
toomanysessions/templates/css/1-body/base.css
toomanysessions/templates/css/1-body/typography.css
toomanysessions/templates/css/2-background/gradients.css
toomanysessions/templates/css/2-background/particles.css
toomanysessions/templates/css/3-layout/containers.css
toomanysessions/templates/css/3-layout/grid.css
toomanysessions/templates/css/4-containers/cards.css
toomanysessions/templates/css/4-containers/modals.css
toomanysessions/templates/css/5-components/forms.css
toomanysessions/templates/css/5-components/icons.css
toomanysessions/templates/css/5-components/status.css
toomanysessions/templates/css/6-buttons/effects.css
toomanysessions/templates/css/6-buttons/primary.css
toomanysessions/templates/css/6-buttons/variants.css
toomanysessions/templates/css/7-utilities/responsive.css
toomanysessions/templates/css/7-utilities/spacing.css
toomanysessions/templates/css/7-utilities/text.css
toomanysessions/templates/css/7-utilities/visibility.css
toomanysessions/templates/css/8-animations/entrance.css
toomanysessions/templates/css/8-animations/microsoft.css
toomanysessions/templates/css/8-animations/particle_anims.css
toomanysessions/templates/css/8-animations/success.css
toomanysessions/templates/css/8-animations/welcome_intro.css
toomanysessions/templates/css/vars.css
toomanysessions/templates/css_documentation.md
toomanysessions/templates/html/content/login_success.html
toomanysessions/templates/html/content/popup.html
toomanysessions/templates/html/content/prompt_for_passkey.html
toomanysessions/templates/html/content/redirect.html
toomanysessions/templates/html/content/unauthorized.html
toomanysessions/templates/html/content/user.html
toomanysessions-0.1.9971.dist-info/LICENSE
toomanysessions-0.1.9971.dist-info/METADATA
toomanysessions-0.1.9971.dist-info/WHEEL
toomanysessions-0.1.9971.dist-info/RECORD
