Metadata-Version: 2.3
Name: toomanysessions
Version: 0.1.9971
Summary: 
Author: Miles Copeland Luce
Requires-Python: >=3.13,<4.0
Classifier: Programming Language :: Python :: 3
Classifier: Programming Language :: Python :: 3.13
Requires-Dist: bcrypt (>=4.3.0,<5.0.0)
Requires-Dist: fastapi (>=0.116.1,<0.117.0)
Requires-Dist: fastj2 (>=0.1.11,<0.2.0)
Requires-Dist: httpx (>=0.28.1,<0.29.0)
Requires-Dist: jinja2 (>=3.1.6,<4.0.0)
Requires-Dist: loguru (>=0.7.3,<0.8.0)
Requires-Dist: pkce (>=1.0.3,<2.0.0)
Requires-Dist: pyzurecli (>=0.7.411,<0.8.0)
Requires-Dist: starlette (>=0.47.2,<0.48.0)
Requires-Dist: toomanyconfigs (>=0.2.865,<0.3.0)
Requires-Dist: toomanyports (>=0.1.1,<0.2.0)
Requires-Dist: toomanythreads (>=0.2.75,<0.3.0)
